{"assets/icons/bike_blue_icon.svg":["assets/icons/bike_blue_icon.svg"],"assets/icons/bike_red_icon.svg":["assets/icons/bike_red_icon.svg"],"assets/icons/bnb_item_1.svg":["assets/icons/bnb_item_1.svg"],"assets/icons/bnb_item_2.svg":["assets/icons/bnb_item_2.svg"],"assets/icons/bnb_item_3.svg":["assets/icons/bnb_item_3.svg"],"assets/icons/location_blue_icon.svg":["assets/icons/location_blue_icon.svg"],"assets/icons/location_map_icon.svg":["assets/icons/location_map_icon.svg"],"assets/icons/location_red_icon.svg":["assets/icons/location_red_icon.svg"],"assets/icons/park_blue_icon.svg":["assets/icons/park_blue_icon.svg"],"assets/icons/park_red_icon.svg":["assets/icons/park_red_icon.svg"],"fonts/SF-Pro-Text-Bold.otf":["fonts/SF-Pro-Text-Bold.otf"],"fonts/SF-Pro-Text-Regular.otf":["fonts/SF-Pro-Text-Regular.otf"],"packages/cupertino_icons/assets/CupertinoIcons.ttf":["packages/cupertino_icons/assets/CupertinoIcons.ttf"]}